scilens_compare/__init__.py
scilens_compare/vectors.py
scilens_compare-0.1.1.dist-info/METADATA
scilens_compare-0.1.1.dist-info/WHEEL
scilens_compare-0.1.1.dist-info/RECORD
