Metadata-Version: 2.1
Name: scilens-compare
Version: 0.1.1
Summary: A CesGensLaB framework for data collecting and deep analysis - Advanced Comparison plugin
Home-page: https://scilens.dev
License: Proprietary
Author: CesGensLaB
Author-email: contact@cesgenlab.fr
Requires-Python: >=3.10,<4.0
Classifier: License :: Other/Proprietary License
Classifier: Programming Language :: Python :: 3
Classifier: Programming Language :: Python :: 3.10
Classifier: Programming Language :: Python :: 3.11
Classifier: Programming Language :: Python :: 3.12
Classifier: Programming Language :: Python :: 3.13
Requires-Dist: numpy (>=2.2.4,<3.0.0)
Project-URL: Documentation, https://scilens.dev/docs
